MANIFEST.in
README.txt
setup.cfg
setup.py
Products/__init__.py
Products.BastionZenoss.egg-info/PKG-INFO
Products.BastionZenoss.egg-info/SOURCES.txt
Products.BastionZenoss.egg-info/dependency_links.txt
Products.BastionZenoss.egg-info/entry_points.txt
Products.BastionZenoss.egg-info/namespace_packages.txt
Products.BastionZenoss.egg-info/not-zip-safe
Products.BastionZenoss.egg-info/requires.txt
Products.BastionZenoss.egg-info/top_level.txt
Products/BastionZenoss/ChangeLog
Products/BastionZenoss/MANIFEST
Products/BastionZenoss/README.txt
Products/BastionZenoss/Reporting.py
Products/BastionZenoss/Zentinel.py
Products/BastionZenoss/__init__.py
Products/BastionZenoss/config.py
Products/BastionZenoss/configure.zcml
Products/BastionZenoss/interfaces.py
Products/BastionZenoss/monkeypatches.py
Products/BastionZenoss/refresh.txt
Products/BastionZenoss/setuphandlers.py
Products/BastionZenoss/version.txt
Products/BastionZenoss/Extensions/Install.py
Products/BastionZenoss/Extensions/__init__.py
Products/BastionZenoss/browser/__init__.py
Products/BastionZenoss/browser/configure.zcml
Products/BastionZenoss/browser/footer.pt
Products/BastionZenoss/browser/quickstart.py
Products/BastionZenoss/browser/sitesetup.py
Products/BastionZenoss/browser/zenfixers.py
Products/BastionZenoss/browser/portlets/__init__.py
Products/BastionZenoss/browser/portlets/configure.zcml
Products/BastionZenoss/browser/portlets/navigation.pt
Products/BastionZenoss/browser/portlets/navigation.py
Products/BastionZenoss/browser/portlets/search.pt
Products/BastionZenoss/browser/portlets/search.py
Products/BastionZenoss/profiles/default/actions.xml
Products/BastionZenoss/profiles/default/import_steps.xml
Products/BastionZenoss/profiles/default/metadata.xml
Products/BastionZenoss/profiles/default/portlets.xml
Products/BastionZenoss/profiles/default/skins.xml
Products/BastionZenoss/profiles/default/toolset.xml
Products/BastionZenoss/profiles/default/types.xml
Products/BastionZenoss/profiles/default/types/ZenReportsTool.xml
Products/BastionZenoss/skins/bastionzenoss/bastion_powered.gif
Products/BastionZenoss/skins/bastionzenoss/bastion_powered.gif.metadata
Products/BastionZenoss/skins/bastionzenoss/lbz_reports_view.pt
Products/BastionZenoss/skins/bastionzenoss/lbz_uptime.pt
Products/BastionZenoss/skins/bastionzenoss/properties_edit.cpy
