Metadata-Version: 1.0
Name: Products.BastionZenoss
Version: 1.0.6
Summary: Plone4Zenoss - run Zenoss within your Enterprise Plone
Home-page: http://www.last-bastion.net/forge/plone4zenoss
Author: Alan Milligan
Author-email: alan.milligan@last-bastion.net
License: ZPL/2.1
Keywords: BastionZenoss Plone4Zenoss Zenoss
Platform: UNKNOWN
Classifier: Framework :: Plone
Classifier: Programming Language :: Python
Classifier: Development Status :: 5 - Production/Stable
Classifier: License :: OSI Approved :: Zope Public License
Classifier: Topic :: System :: Monitoring
Classifier: Topic :: System :: Networking :: Monitoring
